spark_auto_mapper/__init__.py
spark_auto_mapper/py.typed
spark_auto_mapper/automappers/__init__.py
spark_auto_mapper/automappers/automapper.py
spark_auto_mapper/automappers/automapper_analysis_exception.py
spark_auto_mapper/automappers/automapper_base.py
spark_auto_mapper/automappers/automapper_exception.py
spark_auto_mapper/automappers/check_schema_result.py
spark_auto_mapper/automappers/column_spec_wrapper.py
spark_auto_mapper/automappers/columns.py
spark_auto_mapper/automappers/complex.py
spark_auto_mapper/automappers/container.py
spark_auto_mapper/automappers/with_column.py
spark_auto_mapper/automappers/with_column_base.py
spark_auto_mapper/data_types/__init__.py
spark_auto_mapper/data_types/amount.py
spark_auto_mapper/data_types/array.py
spark_auto_mapper/data_types/array_base.py
spark_auto_mapper/data_types/array_distinct.py
spark_auto_mapper/data_types/array_max.py
spark_auto_mapper/data_types/base64.py
spark_auto_mapper/data_types/boolean.py
spark_auto_mapper/data_types/cast_to_type.py
spark_auto_mapper/data_types/coalesce.py
spark_auto_mapper/data_types/column.py
spark_auto_mapper/data_types/column_wrapper.py
spark_auto_mapper/data_types/concat.py
spark_auto_mapper/data_types/cross_column_filter.py
spark_auto_mapper/data_types/data_type_base.py
spark_auto_mapper/data_types/date.py
spark_auto_mapper/data_types/date_format.py
spark_auto_mapper/data_types/datetime.py
spark_auto_mapper/data_types/decimal.py
spark_auto_mapper/data_types/exists.py
spark_auto_mapper/data_types/expression.py
spark_auto_mapper/data_types/field.py
spark_auto_mapper/data_types/filter.py
spark_auto_mapper/data_types/first.py
spark_auto_mapper/data_types/first_valid_column.py
spark_auto_mapper/data_types/flatten.py
spark_auto_mapper/data_types/float.py
spark_auto_mapper/data_types/hash.py
spark_auto_mapper/data_types/hash_abs.py
spark_auto_mapper/data_types/if_.py
spark_auto_mapper/data_types/if_column_exists.py
spark_auto_mapper/data_types/if_not.py
sparkautomapper-3.0.6.dist-info/licenses/LICENSE
sparkautomapper-3.0.6.dist-info/METADATA
sparkautomapper-3.0.6.dist-info/WHEEL
sparkautomapper-3.0.6.dist-info/top_level.txt
sparkautomapper-3.0.6.dist-info/RECORD
